LICENSE
world_economic_outlook/__init__.py
world_economic_outlook/cli.py
world_economic_outlook/search.py
world_economic_outlook/vweo.py
world_economic_outlook/wrappers.py
world_economic_outlook/api/__init__.py
world_economic_outlook/api/base.py
world_economic_outlook/api/endpoints/__init__.py
world_economic_outlook/api/endpoints/afrreo.py
world_economic_outlook/api/endpoints/anea.py
world_economic_outlook/api/endpoints/apdreo.py
world_economic_outlook/api/endpoints/bop.py
world_economic_outlook/api/endpoints/bop_agg.py
world_economic_outlook/api/endpoints/cofer.py
world_economic_outlook/api/endpoints/cpi.py
world_economic_outlook/api/endpoints/ctot.py
world_economic_outlook/api/endpoints/dip.py
world_economic_outlook/api/endpoints/ed.py
world_economic_outlook/api/endpoints/eer.py
world_economic_outlook/api/endpoints/eq.py
world_economic_outlook/api/endpoints/er.py
world_economic_outlook/api/endpoints/fa.py
world_economic_outlook/api/endpoints/fas.py
world_economic_outlook/api/endpoints/fd.py
world_economic_outlook/api/endpoints/fdi.py
world_economic_outlook/api/endpoints/fm.py
world_economic_outlook/api/endpoints/fsibsis.py
world_economic_outlook/api/endpoints/fsic.py
world_economic_outlook/api/endpoints/fsicdm.py
world_economic_outlook/api/endpoints/gdd.py
world_economic_outlook/api/endpoints/gfs_bs.py
world_economic_outlook/api/endpoints/gfs_cofog.py
world_economic_outlook/api/endpoints/gfs_sfcp.py
world_economic_outlook/api/endpoints/gfs_soef.py
world_economic_outlook/api/endpoints/gfs_soo.py
world_economic_outlook/api/endpoints/gfs_ssuc.py
world_economic_outlook/api/endpoints/hpd.py
world_economic_outlook/api/endpoints/icsd.py
world_economic_outlook/api/endpoints/iip.py
world_economic_outlook/api/endpoints/iipcc.py
world_economic_outlook/api/endpoints/il.py
world_economic_outlook/api/endpoints/imts.py
world_economic_outlook/api/endpoints/irfcl.py
world_economic_outlook/api/endpoints/isora_2016_data_pub.py
world_economic_outlook-0.1.1.dist-info/METADATA
world_economic_outlook-0.1.1.dist-info/WHEEL
world_economic_outlook-0.1.1.dist-info/entry_points.txt
world_economic_outlook-0.1.1.dist-info/licenses/LICENSE
world_economic_outlook-0.1.1.dist-info/RECORD
