Metadata-Version: 2.4
Name: world-economic-outlook
Version: 0.1.1
Summary: An IMF World Economic Outlook (WEO) API Client
Author-email: Rob Suomi <robert.suomi@gmail.com>
License-Expression: MIT
License-File: LICENSE
Requires-Python: >=3.9
Requires-Dist: colorama
Requires-Dist: pydantic
Requires-Dist: requests
Requires-Dist: simple-sqlite3
